fichario_client/__init__.py
fichario_client/client.py
fichario_client-0.1.5.dist-info/METADATA
fichario_client-0.1.5.dist-info/WHEEL
fichario_client-0.1.5.dist-info/RECORD
