Metadata-Version: 2.1
Name: fichario-client
Version: 0.1.5
Summary: API Client for Fichar.io
Author: RonaldLopes
Author-email: ronald@fichar.io
Requires-Python: >=3.8,<4.0
Classifier: Programming Language :: Python :: 3
Classifier: Programming Language :: Python :: 3.8
Classifier: Programming Language :: Python :: 3.9
Classifier: Programming Language :: Python :: 3.10
Classifier: Programming Language :: Python :: 3.11
Requires-Dist: httpx (>=0.24.1,<0.25.0)
Requires-Dist: requests (>=2.31.0,<3.0.0)
